django_informer-0.2.2.dist-info/DESCRIPTION.rst
django_informer-0.2.2.dist-info/METADATA
django_informer-0.2.2.dist-info/RECORD
django_informer-0.2.2.dist-info/WHEEL
django_informer-0.2.2.dist-info/entry_points.txt
django_informer-0.2.2.dist-info/metadata.json
django_informer-0.2.2.dist-info/top_level.txt
informer/__init__.py
informer/factories.py
informer/models.py
informer/urls.py
informer/views.py
informer/checker/__init__.py
informer/checker/base.py
informer/checker/cache.py
informer/checker/celery.py
informer/checker/database.py
informer/checker/storage.py
informer/management/__init__.py
informer/management/commands/__init__.py
informer/management/commands/checkinformer.py
informer/migrations/0001_initial.py
informer/migrations/__init__.py
informer/static/django_informer/assets/images/favicon.ico
informer/static/django_informer/assets/styles/django-informer.css
informer/templates/django-informer-base.html
informer/templates/django-informer-detail.html
informer/templates/django-informer-index.html
informer/templates/django-informer-measure.html
