Metadata-Version: 2.0
Name: django-informer
Version: 0.2.2
Summary: a pluggable app to monitoring your own infrastructure and third party services.
Home-page: https://github.com/rodrigobraga/informer
Author: Rodrigo Braga
Author-email: rodrigobraga@msn.com
License: MIT
Keywords: django monitoring reporting
Platform: any
Classifier: Development Status :: 3 - Alpha
Classifier: Intended Audience :: Developers
Classifier: Topic :: Software Development :: Libraries
Classifier: Framework :: Django
Classifier: License :: OSI Approved :: MIT License
Classifier: Programming Language :: Python :: 3.4
Provides-Extra: dev
Requires-Dist: check-manifest; extra == 'dev'
Provides-Extra: test
Requires-Dist: coverage; extra == 'test'
